{
  "version": "1.0.0",
  "links": [
    {"source":"HTML","target":"CSS","strength":1},
    {"source":"CSS","target":"JavaScript","strength":1},
    {"source":"CSS","target":"SASS/SCSS","strength":0.9},
    {"source":"CSS","target":"Tailwind CSS","strength":0.8},
    {"source":"CSS","target":"Bootstrap","strength":0.8},
    {"source":"JavaScript","target":"TypeScript","strength":0.9},
    {"source":"JavaScript","target":"React","strength":1},
    {"source":"JavaScript","target":"Vue.js","strength":1},
    {"source":"JavaScript","target":"Angular","strength":1},
    {"source":"TypeScript","target":"React","strength":0.9},
    {"source":"TypeScript","target":"Angular","strength":1},
    {"source":"Tailwind CSS","target":"React","strength":0.7},
    {"source":"Tailwind CSS","target":"Vue.js","strength":0.7},
    {"source":"JavaScript","target":"Node.js","strength":1},
    {"source":"Node.js","target":"Express.js","strength":1},
    {"source":"TypeScript","target":"Node.js","strength":0.8},
    {"source":"Atomic Design","target":"React","strength":0.9},
    {"source":"Atomic Design","target":"Vue.js","strength":0.85},
    {"source":"Atomic Design","target":"Component-Based","strength":0.95},
    {"source":"Atomic Design","target":"Figma","strength":0.8},
    {"source":"Component-Based","target":"React","strength":1},
    {"source":"Component-Based","target":"Vue.js","strength":1},
    {"source":"Component-Based","target":"Angular","strength":1},
    {"source":"State Management","target":"React","strength":0.95},
    {"source":"State Management","target":"Vue.js","strength":0.9},
    {"source":"State Management","target":"Angular","strength":0.85},
    {"source":"SSR/SSG","target":"React","strength":0.95},
    {"source":"SSR/SSG","target":"Vue.js","strength":0.9},
    {"source":"SSR/SSG","target":"Node.js","strength":0.85},
    {"source":"PWA","target":"JavaScript","strength":0.9},
    {"source":"PWA","target":"React","strength":0.85},
    {"source":"PWA","target":"Vue.js","strength":0.85},
    {"source":"Mobile First","target":"CSS","strength":0.95},
    {"source":"Mobile First","target":"Responsive Design","strength":1},
    {"source":"Mobile First","target":"Tailwind CSS","strength":0.85},
    {"source":"Responsive Design","target":"CSS","strength":1},
    {"source":"Responsive Design","target":"Bootstrap","strength":0.9},
    {"source":"Responsive Design","target":"Tailwind CSS","strength":0.9},
    {"source":"Python","target":"Django","strength":1},
    {"source":"Python","target":"Flask","strength":1},
    {"source":"Python","target":"FastAPI","strength":1},
    {"source":"Python","target":"Pandas","strength":0.9},
    {"source":"Python","target":"Data Science","strength":0.95},
    {"source":"Python","target":"Machine Learning","strength":0.9},
    {"source":"Python","target":"Pytest","strength":0.8},
    {"source":"PHP","target":"Laravel","strength":1},
    {"source":"PHP","target":"MySQL","strength":0.9},
    {"source":"Java","target":"Spring Boot","strength":1},
    {"source":"Java","target":"JUnit","strength":0.9},
    {"source":"C#/.NET","target":"Azure","strength":0.7},
    {"source":"MVC","target":"Django","strength":0.95},
    {"source":"MVC","target":"Laravel","strength":0.95},
    {"source":"MVC","target":"Spring Boot","strength":0.9},
    {"source":"MVC","target":"Express.js","strength":0.8},
    {"source":"MVC","target":"Angular","strength":0.85},
    {"source":"Clean Architecture","target":"SOLID","strength":0.95},
    {"source":"Clean Architecture","target":"DDD","strength":0.9},
    {"source":"Clean Architecture","target":"Design Patterns","strength":0.9},
    {"source":"Clean Architecture","target":"Repository Pattern","strength":0.95},
    {"source":"DDD","target":"Microservices","strength":0.9},
    {"source":"DDD","target":"CQRS","strength":0.9},
    {"source":"DDD","target":"Design Patterns","strength":0.85},
    {"source":"SOLID","target":"Clean Code","strength":0.95},
    {"source":"SOLID","target":"Design Patterns","strength":0.9},
    {"source":"SOLID","target":"Java","strength":0.8},
    {"source":"SOLID","target":"C#/.NET","strength":0.8},
    {"source":"Design Patterns","target":"Java","strength":0.9},
    {"source":"Design Patterns","target":"Python","strength":0.8},
    {"source":"Design Patterns","target":"C#/.NET","strength":0.85},
    {"source":"ORM","target":"Django","strength":0.95},
    {"source":"ORM","target":"Laravel","strength":0.95},
    {"source":"ORM","target":"Spring Boot","strength":0.9},
    {"source":"ORM","target":"SQL","strength":0.9},
    {"source":"ORM","target":"PostgreSQL","strength":0.85},
    {"source":"Repository Pattern","target":"ORM","strength":0.9},
    {"source":"Repository Pattern","target":"Design Patterns","strength":0.85},
    {"source":"CQRS","target":"Microservices","strength":0.9},
    {"source":"CQRS","target":"API REST","strength":0.8},
    {"source":"Merise","target":"SQL","strength":0.95},
    {"source":"Merise","target":"Entity-Relationship","strength":0.95},
    {"source":"Merise","target":"Normalisation","strength":0.9},
    {"source":"UML","target":"Merise","strength":0.7},
    {"source":"UML","target":"DDD","strength":0.8},
    {"source":"UML","target":"Design Patterns","strength":0.75},
    {"source":"UML","target":"Clean Architecture","strength":0.7},
    {"source":"Normalisation","target":"SQL","strength":0.95},
    {"source":"Normalisation","target":"PostgreSQL","strength":0.9},
    {"source":"Normalisation","target":"MySQL","strength":0.9},
    {"source":"ACID","target":"PostgreSQL","strength":0.95},
    {"source":"ACID","target":"MySQL","strength":0.95},
    {"source":"ACID","target":"SQL","strength":0.9},
    {"source":"Indexation","target":"PostgreSQL","strength":0.95},
    {"source":"Indexation","target":"MySQL","strength":0.95},
    {"source":"Indexation","target":"MongoDB","strength":0.85},
    {"source":"Indexation","target":"Elasticsearch","strength":0.9},
    {"source":"Sharding","target":"MongoDB","strength":0.95},
    {"source":"Sharding","target":"PostgreSQL","strength":0.8},
    {"source":"Sharding","target":"Réplication","strength":0.9},
    {"source":"Sharding","target":"Microservices","strength":0.85},
    {"source":"Réplication","target":"PostgreSQL","strength":0.9},
    {"source":"Réplication","target":"MySQL","strength":0.9},
    {"source":"Réplication","target":"MongoDB","strength":0.9},
    {"source":"Réplication","target":"Redis","strength":0.85},
    {"source":"Entity-Relationship","target":"SQL","strength":0.95},
    {"source":"Entity-Relationship","target":"UML","strength":0.8},
    {"source":"TDD","target":"Jest","strength":0.9},
    {"source":"TDD","target":"Pytest","strength":0.9},
    {"source":"TDD","target":"JUnit","strength":0.9},
    {"source":"TDD","target":"Clean Code","strength":0.9},
    {"source":"TDD","target":"Refactoring","strength":0.95},
    {"source":"BDD","target":"TDD","strength":0.9},
    {"source":"BDD","target":"Cypress","strength":0.85},
    {"source":"BDD","target":"Agile/Scrum","strength":0.8},
    {"source":"Clean Code","target":"SOLID","strength":0.95},
    {"source":"Clean Code","target":"Refactoring","strength":0.95},
    {"source":"Clean Code","target":"Code Review","strength":0.9},
    {"source":"Code Review","target":"Git","strength":0.9},
    {"source":"Code Review","target":"GitHub","strength":0.95},
    {"source":"Code Review","target":"GitLab","strength":0.95},
    {"source":"Refactoring","target":"Design Patterns","strength":0.85},
    {"source":"Refactoring","target":"VS Code","strength":0.7},
    {"source":"Refactoring","target":"IntelliJ IDEA","strength":0.85},
    {"source":"Documentation","target":"API REST","strength":0.85},
    {"source":"Documentation","target":"Postman","strength":0.9},
    {"source":"Documentation","target":"GitHub","strength":0.8},
    {"source":"React","target":"API REST","strength":0.9},
    {"source":"Vue.js","target":"API REST","strength":0.9},
    {"source":"Angular","target":"API REST","strength":0.9},
    {"source":"React","target":"GraphQL","strength":0.7},
    {"source":"React","target":"Node.js","strength":0.8},
    {"source":"API REST","target":"Express.js","strength":0.95},
    {"source":"API REST","target":"Django","strength":0.95},
    {"source":"API REST","target":"FastAPI","strength":0.95},
    {"source":"API REST","target":"Spring Boot","strength":0.95},
    {"source":"API REST","target":"Laravel","strength":0.9},
    {"source":"GraphQL","target":"Node.js","strength":0.8},
    {"source":"Django","target":"PostgreSQL","strength":0.95},
    {"source":"Express.js","target":"MongoDB","strength":0.85},
    {"source":"Express.js","target":"PostgreSQL","strength":0.8},
    {"source":"FastAPI","target":"PostgreSQL","strength":0.9},
    {"source":"Spring Boot","target":"PostgreSQL","strength":0.9},
    {"source":"Laravel","target":"MySQL","strength":0.95},
    {"source":"Node.js","target":"MongoDB","strength":0.85},
    {"source":"SQL","target":"PostgreSQL","strength":1},
    {"source":"SQL","target":"MySQL","strength":1},
    {"source":"SQL","target":"SQLite","strength":1},
    {"source":"PostgreSQL","target":"Redis","strength":0.6},
    {"source":"MongoDB","target":"Redis","strength":0.6},
    {"source":"SQL","target":"Data Science","strength":0.8},
    {"source":"Elasticsearch","target":"Microservices","strength":0.7},
    {"source":"Data Science","target":"Machine Learning","strength":0.95},
    {"source":"Data Science","target":"Pandas","strength":0.95},
    {"source":"Data Science","target":"Power BI/Tableau","strength":0.8},
    {"source":"Pandas","target":"Machine Learning","strength":0.8},
    {"source":"Git","target":"GitHub","strength":1},
    {"source":"Git","target":"GitLab","strength":1},
    {"source":"Git","target":"CI/CD","strength":0.95},
    {"source":"GitHub","target":"CI/CD","strength":0.9},
    {"source":"GitLab","target":"CI/CD","strength":0.95},
    {"source":"CI/CD","target":"Docker","strength":0.95},
    {"source":"Docker","target":"Kubernetes","strength":0.95},
    {"source":"Docker","target":"Linux","strength":0.9},
    {"source":"Linux","target":"Nginx","strength":0.85},
    {"source":"Kubernetes","target":"AWS","strength":0.85},
    {"source":"Kubernetes","target":"GCP","strength":0.9},
    {"source":"Kubernetes","target":"Azure","strength":0.85},
    {"source":"Terraform","target":"AWS","strength":0.9},
    {"source":"Terraform","target":"Azure","strength":0.9},
    {"source":"Terraform","target":"GCP","strength":0.9},
    {"source":"Docker","target":"AWS","strength":0.8},
    {"source":"Linux","target":"AWS","strength":0.85},
    {"source":"OWASP Top 10","target":"Pentesting","strength":0.95},
    {"source":"OWASP Top 10","target":"DevSecOps","strength":0.9},
    {"source":"OWASP Top 10","target":"Django","strength":0.7},
    {"source":"OWASP Top 10","target":"Express.js","strength":0.7},
    {"source":"OWASP Top 10","target":"Laravel","strength":0.7},
    {"source":"Pentesting","target":"Linux","strength":0.9},
    {"source":"Pentesting","target":"Sécurité Réseau","strength":0.95},
    {"source":"Pentesting","target":"Python","strength":0.7},
    {"source":"Cryptographie","target":"SSL/TLS","strength":1},
    {"source":"Cryptographie","target":"OAuth 2.0 / JWT","strength":0.85},
    {"source":"Cryptographie","target":"Python","strength":0.6},
    {"source":"SSL/TLS","target":"Nginx","strength":0.95},
    {"source":"SSL/TLS","target":"API REST","strength":0.9},
    {"source":"SSL/TLS","target":"AWS","strength":0.7},
    {"source":"OAuth 2.0 / JWT","target":"API REST","strength":0.95},
    {"source":"OAuth 2.0 / JWT","target":"React","strength":0.8},
    {"source":"OAuth 2.0 / JWT","target":"Node.js","strength":0.85},
    {"source":"OAuth 2.0 / JWT","target":"IAM","strength":0.9},
    {"source":"Firewall / WAF","target":"Nginx","strength":0.85},
    {"source":"Firewall / WAF","target":"AWS","strength":0.8},
    {"source":"Firewall / WAF","target":"Sécurité Réseau","strength":0.95},
    {"source":"Firewall / WAF","target":"Linux","strength":0.8},
    {"source":"SIEM / SOC","target":"Elasticsearch","strength":0.9},
    {"source":"SIEM / SOC","target":"Sécurité Réseau","strength":0.9},
    {"source":"SIEM / SOC","target":"RGPD / Compliance","strength":0.85},
    {"source":"IAM","target":"AWS","strength":0.85},
    {"source":"IAM","target":"Azure","strength":0.85},
    {"source":"IAM","target":"Zero Trust","strength":0.9},
    {"source":"IAM","target":"RGPD / Compliance","strength":0.8},
    {"source":"Zero Trust","target":"Microservices","strength":0.85},
    {"source":"Zero Trust","target":"Kubernetes","strength":0.8},
    {"source":"Zero Trust","target":"Sécurité Réseau","strength":0.9},
    {"source":"DevSecOps","target":"CI/CD","strength":1},
    {"source":"DevSecOps","target":"Docker","strength":0.9},
    {"source":"DevSecOps","target":"Git","strength":0.85},
    {"source":"DevSecOps","target":"DevOps Culture","strength":0.95},
    {"source":"Sécurité Réseau","target":"Linux","strength":0.9},
    {"source":"Sécurité Réseau","target":"AWS","strength":0.75},
    {"source":"RGPD / Compliance","target":"PostgreSQL","strength":0.7},
    {"source":"RGPD / Compliance","target":"MongoDB","strength":0.7},
    {"source":"VS Code","target":"Git","strength":0.8},
    {"source":"VS Code","target":"JavaScript","strength":0.8},
    {"source":"VS Code","target":"Python","strength":0.8},
    {"source":"VS Code","target":"TypeScript","strength":0.8},
    {"source":"IntelliJ IDEA","target":"Java","strength":0.95},
    {"source":"Postman","target":"API REST","strength":0.95},
    {"source":"npm/yarn","target":"Node.js","strength":1},
    {"source":"npm/yarn","target":"React","strength":0.9},
    {"source":"Webpack/Vite","target":"React","strength":0.9},
    {"source":"Webpack/Vite","target":"JavaScript","strength":0.9},
    {"source":"ESLint/Prettier","target":"JavaScript","strength":0.9},
    {"source":"ESLint/Prettier","target":"TypeScript","strength":0.9},
    {"source":"ESLint/Prettier","target":"Clean Code","strength":0.8},
    {"source":"Jest","target":"React","strength":0.95},
    {"source":"Jest","target":"JavaScript","strength":0.9},
    {"source":"Cypress","target":"React","strength":0.85},
    {"source":"Cypress","target":"Vue.js","strength":0.85},
    {"source":"Selenium","target":"Java","strength":0.8},
    {"source":"Selenium","target":"Python","strength":0.8},
    {"source":"JUnit","target":"Spring Boot","strength":0.9},
    {"source":"Pytest","target":"Django","strength":0.9},
    {"source":"Pytest","target":"FastAPI","strength":0.9},
    {"source":"Microservices","target":"Docker","strength":0.95},
    {"source":"Microservices","target":"Kubernetes","strength":0.95},
    {"source":"Microservices","target":"API REST","strength":0.9},
    {"source":"WebSockets","target":"Node.js","strength":0.85},
    {"source":"WebSockets","target":"Redis","strength":0.7},
    {"source":"Agile/Scrum","target":"Git","strength":0.7},
    {"source":"Agile/Scrum","target":"Kanban","strength":0.85},
    {"source":"DevOps Culture","target":"CI/CD","strength":1},
    {"source":"DevOps Culture","target":"Docker","strength":0.95},
    {"source":"DevOps Culture","target":"Kubernetes","strength":0.9},
    {"source":"DevOps Culture","target":"Terraform","strength":0.9},
    {"source":"Kanban","target":"Agile/Scrum","strength":0.85},
    {"source":"Figma","target":"UX/UI Design","strength":0.95},
    {"source":"UX/UI Design","target":"React","strength":0.7},
    {"source":"UX/UI Design","target":"CSS","strength":0.75},
    {"source":"Figma","target":"React","strength":0.6}
  ]
}
